<?xml version="1.0" encoding="utf-8"?>
<Override>
  <Charactervariant inherit="BNZHuman_HX" displayname="" speciesname="SpikeThunderhuman_pirate" group="pirate">
    <health Vitality="250" />
    <ai sight="100" hearing="100" />
    <attack damagemultiplier="0" rangemultiplier="3" impactmultiplier="2" />
    <inventory arrowslot="9" Slots="Card, Headset, Head, InnerClothes, OuterClothes, LeftHand, RightHand, Bag, Any, Any, Any, Any, Any, Any, Any, Any, Any, Any, HealthInterface" Accessiblewhenalive="True" Commonness="3">
      <Item identifier="idcard" slot="Card" />
      <Item identifier="ballistichelmet1" slot="Head" />
      <Item identifier="separatistcommoner1" slot="InnerClothes" />
      <Item identifier="bodyarmor" slot="OuterClothes" />
      <Item identifier="SpikeThunder_TLAI" slot="RightHand+LeftHand" />
    </inventory>
    <StatusEffect type="OnDeath" target="This">
      <SpawnItem identifiers="coalitioncommendation" spawnposition="This" probability="0.1" />
    </StatusEffect>
    <StatusEffect type="OnDeath" target="This" disabledeltatime="true" stackable="false" delay="3">
      <removecharacter />
    </StatusEffect>
  </Charactervariant>
</Override>